Workbook

Sheet Instrucciones
A1: Registro de resultados de pruebas — Dulce Día
A3: Propósito | B3: Registrar la ejecución real de los 55 casos del Plan de Pruebas, los defectos encontrados y el cumplimiento de los criterios de salida.
A4: Importante | B4: Este archivo NO contiene resultados. Todos los casos parten como “Por ejecutar”. Cada resultado debe ser el que realmente se obtenga al probar el sistema y debe respaldarse con una evidencia en el repositorio Git.
A5: Celdas que se completan | B5: Las celdas con fondo amarillo y letra azul (hoja Casos: columnas H a N; hoja Defectos: columnas B a K; hoja Ciclos: columnas C, D, E y K; hoja Resumen: B16). Todo lo demás se calcula solo.
A6: Cómo registrar un caso | B6: 1) Ejecutar el caso con los pasos y datos indicados. 2) Guardar la evidencia (captura, registro o respuesta de la API) en pruebas/evidencias/CP-XX/ del repositorio. 3) Elegir Ciclo, Estado, Fecha y Ejecutado por. 4) Describir el resultado obtenido y la ruta de la evidencia. 5) Si falló, registrar el defecto en la hoja Defectos y poner su ID en la columna Defecto asociado.
A7: Estados | B7: Por ejecutar: aún no probado. Aprobado: el resultado coincide con lo esperado. Fallido: no coincide (requiere defecto). Bloqueado: no se pudo probar por una dependencia o falla previa.
A8: Hojas | B8: Resumen (indicadores y criterios de salida) · Casos (los 55 casos) · Defectos (hasta 30) · Ciclos (avance por ciclo de prueba).
A10: Ejemplo de llenado (ilustrativo, no es un resultado real)
A11: Campo | B11: Ejemplo de valor
A12: Ciclo | B12: Ciclo 1
A13: Estado | B13: Aprobado
A14: Fecha de ejecución | B14: dd/mm/aaaa (por ejemplo, 05/11/2026)
A15: Ejecutado por | B15: Camilo Rojas
A16: Resultado obtenido | B16: El pedido se guardó con estado Pendiente y apareció en la agenda de la fecha elegida.
A17: Evidencia (ruta en Git) | B17: pruebas/evidencias/CP-06/agenda_pedido.png
A18: Defecto asociado | B18: — (vacío si el caso aprobó) o DEF-001 si falló

Sheet Resumen
A1: Resumen de resultados de pruebas — Dulce Día
A2: Todos los valores se calculan automáticamente desde las hojas Casos y Defectos. No hay que escribir nada en esta hoja, salvo la celda B16 (acta de aceptación del cliente).
A4: Estado general de los casos | B4: Cantidad | C4: % del total
A5: Total de casos de prueba | B5: =COUNTA(Casos!$A$2:$A$56) -> 55 | C5: =IF($B$5=0,0,B5/$B$5) -> 1
A6: Por ejecutar | B6: =COUNTIF(Casos!$I$2:$I$56,"Por ejecutar") -> 55 | C6: =IF($B$5=0,0,B6/$B$5) -> 1
A7: Aprobados | B7: =COUNTIF(Casos!$I$2:$I$56,"Aprobado") -> 0 | C7: =IF($B$5=0,0,B7/$B$5) -> 0
A8: Fallidos | B8: =COUNTIF(Casos!$I$2:$I$56,"Fallido") -> 0 | C8: =IF($B$5=0,0,B8/$B$5) -> 0
A9: Bloqueados | B9: =COUNTIF(Casos!$I$2:$I$56,"Bloqueado") -> 0 | C9: =IF($B$5=0,0,B9/$B$5) -> 0
A10: Casos ejecutados (aprobados + fallidos) | B10: =B7+B8 -> 0 | C10: =IF($B$5=0,0,B10/$B$5) -> 0
A12: Criterio de salida (sección 6 del Plan de Pruebas) | B12: Valor actual | C12: Meta | D12: Resultado
A13: Casos de prioridad alta ejecutados (meta: todos los de prioridad alta) | B13: =COUNTIFS(Casos!$G$2:$G$56,"Alta",Casos!$I$2:$I$56,"Aprobado")+COUNTIFS(Casos!$G$2:$G$56,"Alta",Casos!$I$2:$I$56,"Fallido") -> 0 | C13: =COUNTIF(Casos!$G$2:$G$56,"Alta") -> 32 | D13: =IF(B13=C13,"CUMPLE","NO CUMPLE") -> NO CUMPLE
A14: Casos aprobados sobre el total | B14: =C7 -> 0 | C14: 0.9 | D14: =IF(B14>=C14,"CUMPLE","NO CUMPLE") -> NO CUMPLE
A15: Defectos críticos o altos abiertos | B15: =COUNTIFS(Defectos!$F$2:$F$31,"Crítica",Defectos!$G$2:$G$31,"<>Cerrado")+COUNTIFS(Defectos!$F$2:$F$31,"Alta",Defectos!$G$2:$G$31,"<>Cerrado") -> 0 | C15: 0 | D15: =IF(B15<=C15,"CUMPLE","NO CUMPLE") -> CUMPLE
A16: Acta de aceptación del cliente firmada | B16: No | C16: Sí | D16: =IF(B16="Sí","CUMPLE","NO CUMPLE") -> NO CUMPLE
A17: Cierre de pruebas | D17: =IF(AND(D13="CUMPLE",D14="CUMPLE",D15="CUMPLE",D16="CUMPLE"),"CUMPLE","NO CUMPLE") -> NO CUMPLE
A18: La meta de 90% de aprobación y el criterio de aceptación son los propuestos en el Plan de Pruebas; ajústalos si el docente o el cliente definen otros.
A20: Defectos | B20: Cantidad
A21: Defectos registrados | B21: =COUNTA(Defectos!$C$2:$C$31) -> 0
A22: Defectos abiertos (no cerrados) | B22: =COUNTIFS(Defectos!$C$2:$C$31,"<>",Defectos!$G$2:$G$31,"<>Cerrado") -> 0
A23: Defectos de severidad crítica | B23: =COUNTIF(Defectos!$F$2:$F$31,"Crítica") -> 0
A24: Defectos de severidad alta | B24: =COUNTIF(Defectos!$F$2:$F$31,"Alta") -> 0
A25: Defectos de severidad media | B25: =COUNTIF(Defectos!$F$2:$F$31,"Media") -> 0
A26: Defectos de severidad baja | B26: =COUNTIF(Defectos!$F$2:$F$31,"Baja") -> 0
A28: Resultados por módulo | B28: Total | C28: Aprobados | D28: Fallidos | E28: Bloqueados | F28: Por ejecutar | G28: % aprobados
A29: A. Autenticación y control de acceso | B29: =COUNTIF(Casos!$B$2:$B$56,$A29) -> 5 | C29: =COUNTIFS(Casos!$B$2:$B$56,$A29,Casos!$I$2:$I$56,"Aprobado") -> 0 | D29: =COUNTIFS(Casos!$B$2:$B$56,$A29,Casos!$I$2:$I$56,"Fallido") -> 0 | E29: =COUNTIFS(Casos!$B$2:$B$56,$A29,Casos!$I$2:$I$56,"Bloqueado") -> 0 | F29: =COUNTIFS(Casos!$B$2:$B$56,$A29,Casos!$I$2:$I$56,"Por ejecutar") -> 5 | G29: =IF(B29=0,0,C29/B29) -> 0
A30: B. Registro y gestión de pedidos | B30: =COUNTIF(Casos!$B$2:$B$56,$A30) -> 8 | C30: =COUNTIFS(Casos!$B$2:$B$56,$A30,Casos!$I$2:$I$56,"Aprobado") -> 0 | D30: =COUNTIFS(Casos!$B$2:$B$56,$A30,Casos!$I$2:$I$56,"Fallido") -> 0 | E30: =COUNTIFS(Casos!$B$2:$B$56,$A30,Casos!$I$2:$I$56,"Bloqueado") -> 0 | F30: =COUNTIFS(Casos!$B$2:$B$56,$A30,Casos!$I$2:$I$56,"Por ejecutar") -> 8 | G30: =IF(B30=0,0,C30/B30) -> 0
A31: C. Estados, abonos y saldos | B31: =COUNTIF(Casos!$B$2:$B$56,$A31) -> 8 | C31: =COUNTIFS(Casos!$B$2:$B$56,$A31,Casos!$I$2:$I$56,"Aprobado") -> 0 | D31: =COUNTIFS(Casos!$B$2:$B$56,$A31,Casos!$I$2:$I$56,"Fallido") -> 0 | E31: =COUNTIFS(Casos!$B$2:$B$56,$A31,Casos!$I$2:$I$56,"Bloqueado") -> 0 | F31: =COUNTIFS(Casos!$B$2:$B$56,$A31,Casos!$I$2:$I$56,"Por ejecutar") -> 8 | G31: =IF(B31=0,0,C31/B31) -> 0
A32: D. Comprobantes y notificaciones push | B32: =COUNTIF(Casos!$B$2:$B$56,$A32) -> 5 | C32: =COUNTIFS(Casos!$B$2:$B$56,$A32,Casos!$I$2:$I$56,"Aprobado") -> 0 | D32: =COUNTIFS(Casos!$B$2:$B$56,$A32,Casos!$I$2:$I$56,"Fallido") -> 0 | E32: =COUNTIFS(Casos!$B$2:$B$56,$A32,Casos!$I$2:$I$56,"Bloqueado") -> 0 | F32: =COUNTIFS(Casos!$B$2:$B$56,$A32,Casos!$I$2:$I$56,"Por ejecutar") -> 5 | G32: =IF(B32=0,0,C32/B32) -> 0
A33: E. Catálogo, precios y calendario (administración) | B33: =COUNTIF(Casos!$B$2:$B$56,$A33) -> 8 | C33: =COUNTIFS(Casos!$B$2:$B$56,$A33,Casos!$I$2:$I$56,"Aprobado") -> 0 | D33: =COUNTIFS(Casos!$B$2:$B$56,$A33,Casos!$I$2:$I$56,"Fallido") -> 0 | E33: =COUNTIFS(Casos!$B$2:$B$56,$A33,Casos!$I$2:$I$56,"Bloqueado") -> 0 | F33: =COUNTIFS(Casos!$B$2:$B$56,$A33,Casos!$I$2:$I$56,"Por ejecutar") -> 8 | G33: =IF(B33=0,0,C33/B33) -> 0
A34: F. Portal web e-commerce | B34: =COUNTIF(Casos!$B$2:$B$56,$A34) -> 4 | C34: =COUNTIFS(Casos!$B$2:$B$56,$A34,Casos!$I$2:$I$56,"Aprobado") -> 0 | D34: =COUNTIFS(Casos!$B$2:$B$56,$A34,Casos!$I$2:$I$56,"Fallido") -> 0 | E34: =COUNTIFS(Casos!$B$2:$B$56,$A34,Casos!$I$2:$I$56,"Bloqueado") -> 0 | F34: =COUNTIFS(Casos!$B$2:$B$56,$A34,Casos!$I$2:$I$56,"Por ejecutar") -> 4 | G34: =IF(B34=0,0,C34/B34) -> 0
A35: G. Chatbot con inteligencia artificial | B35: =COUNTIF(Casos!$B$2:$B$56,$A35) -> 4 | C35: =COUNTIFS(Casos!$B$2:$B$56,$A35,Casos!$I$2:$I$56,"Aprobado") -> 0 | D35: =COUNTIFS(Casos!$B$2:$B$56,$A35,Casos!$I$2:$I$56,"Fallido") -> 0 | E35: =COUNTIFS(Casos!$B$2:$B$56,$A35,Casos!$I$2:$I$56,"Bloqueado") -> 0 | F35: =COUNTIFS(Casos!$B$2:$B$56,$A35,Casos!$I$2:$I$56,"Por ejecutar") -> 4 | G35: =IF(B35=0,0,C35/B35) -> 0
A36: H. Reportes e historial de pagos | B36: =COUNTIF(Casos!$B$2:$B$56,$A36) -> 3 | C36: =COUNTIFS(Casos!$B$2:$B$56,$A36,Casos!$I$2:$I$56,"Aprobado") -> 0 | D36: =COUNTIFS(Casos!$B$2:$B$56,$A36,Casos!$I$2:$I$56,"Fallido") -> 0 | E36: =COUNTIFS(Casos!$B$2:$B$56,$A36,Casos!$I$2:$I$56,"Bloqueado") -> 0 | F36: =COUNTIFS(Casos!$B$2:$B$56,$A36,Casos!$I$2:$I$56,"Por ejecutar") -> 3 | G36: =IF(B36=0,0,C36/B36) -> 0
A37: I. Integración, despliegue y aceptación | B37: =COUNTIF(Casos!$B$2:$B$56,$A37) -> 3 | C37: =COUNTIFS(Casos!$B$2:$B$56,$A37,Casos!$I$2:$I$56,"Aprobado") -> 0 | D37: =COUNTIFS(Casos!$B$2:$B$56,$A37,Casos!$I$2:$I$56,"Fallido") -> 0 | E37: =COUNTIFS(Casos!$B$2:$B$56,$A37,Casos!$I$2:$I$56,"Bloqueado") -> 0 | F37: =COUNTIFS(Casos!$B$2:$B$56,$A37,Casos!$I$2:$I$56,"Por ejecutar") -> 3 | G37: =IF(B37=0,0,C37/B37) -> 0
A38: J. Pruebas no funcionales | B38: =COUNTIF(Casos!$B$2:$B$56,$A38) -> 7 | C38: =COUNTIFS(Casos!$B$2:$B$56,$A38,Casos!$I$2:$I$56,"Aprobado") -> 0 | D38: =COUNTIFS(Casos!$B$2:$B$56,$A38,Casos!$I$2:$I$56,"Fallido") -> 0 | E38: =COUNTIFS(Casos!$B$2:$B$56,$A38,Casos!$I$2:$I$56,"Bloqueado") -> 0 | F38: =COUNTIFS(Casos!$B$2:$B$56,$A38,Casos!$I$2:$I$56,"Por ejecutar") -> 7 | G38: =IF(B38=0,0,C38/B38) -> 0
A39: Total | B39: =SUM(B29:B38) -> 55 | C39: =SUM(C29:C38) -> 0 | D39: =SUM(D29:D38) -> 0 | E39: =SUM(E29:E38) -> 0 | F39: =SUM(F29:F38) -> 55 | G39: =IF(B39=0,0,C39/B39) -> 0
A41: Aporte individual en las pruebas | B41: Casos ejecutados | C41: Aprobados | D41: Fallidos | E41: Defectos asignados
A42: Renato Carreño | B42: =C42+D42 -> 0 | C42: =COUNTIFS(Casos!$K$2:$K$56,$A42,Casos!$I$2:$I$56,"Aprobado") -> 0 | D42: =COUNTIFS(Casos!$K$2:$K$56,$A42,Casos!$I$2:$I$56,"Fallido") -> 0 | E42: =COUNTIFS(Defectos!$H$2:$H$31,$A42,Defectos!$C$2:$C$31,"<>") -> 0
A43: Camilo Rojas | B43: =C43+D43 -> 0 | C43: =COUNTIFS(Casos!$K$2:$K$56,$A43,Casos!$I$2:$I$56,"Aprobado") -> 0 | D43: =COUNTIFS(Casos!$K$2:$K$56,$A43,Casos!$I$2:$I$56,"Fallido") -> 0 | E43: =COUNTIFS(Defectos!$H$2:$H$31,$A43,Defectos!$C$2:$C$31,"<>") -> 0
A44: Jorge Berroeta | B44: =C44+D44 -> 0 | C44: =COUNTIFS(Casos!$K$2:$K$56,$A44,Casos!$I$2:$I$56,"Aprobado") -> 0 | D44: =COUNTIFS(Casos!$K$2:$K$56,$A44,Casos!$I$2:$I$56,"Fallido") -> 0 | E44: =COUNTIFS(Defectos!$H$2:$H$31,$A44,Defectos!$C$2:$C$31,"<>") -> 0
A45: Sirve como evidencia de la participación de cada integrante; debe coincidir con los commits y evidencias del repositorio Git.

Sheet Casos
A1: ID | B1: Módulo | C1: Requisito / HU | D1: Caso de prueba | E1: Pasos y datos | F1: Resultado esperado | G1: Prioridad | H1: Ciclo | I1: Estado | J1: Fecha de ejecución | K1: Ejecutado por | L1: Resultado obtenido | M1: Evidencia (ruta en Git) | N1: Defecto asociado
A2: CP-01 | B2: A. Autenticación y control de acceso | C2: RF-10 · HU-08 | D2: Inicio de sesión con credenciales válidas | E2: 1) Abrir la app. 2) Ingresar usuario y contraseña de un usuario activo con rol Atención. 3) Presionar ENTRAR. | F2: Se accede a la pantalla principal y solo se muestran las funciones del rol asignado. | G2: Alta | H2: Ciclo 1 | I2: Por ejecutar | J2: 46328 | K2: Renato Carreño
A3: CP-02 | B3: A. Autenticación y control de acceso | C3: RF-10 · HU-08 | D3: Inicio de sesión con credenciales inválidas | E3: Probar contraseña incorrecta, usuario inexistente y campos vacíos. | F3: Se rechaza el acceso con un mensaje de error claro, sin revelar cuál de los datos falló. | G3: Alta | H3: Ciclo 1 | I3: Por ejecutar | J3: 46328 | K3: Renato Carreño
A4: CP-03 | B4: A. Autenticación y control de acceso | C4: RF-10 · RF-11 · HU-07 · HU-08 | D4: Restricción de funciones por rol | E4: Autenticarse con rol Producción e intentar editar precios, modificar el catálogo o bloquear días. | F4: La acción se deniega o la opción no está disponible; no se modifica ningún dato. | G4: Alta | H4: Ciclo 1 | I4: Por ejecutar | J4: 46329 | K4: Renato Carreño
A5: CP-04 | B5: A. Autenticación y control de acceso | C5: RNF-05 | D5: Acceso directo al panel de administración sin sesión | E5: Sin autenticarse, abrir la URL del panel /admin y sus subrutas. | F5: Se redirige al inicio de sesión o se deniega el acceso. | G5: Alta | H5: Ciclo 1 | I5: Por ejecutar | J5: 46329 | K5: Renato Carreño
A6: CP-05 | B6: A. Autenticación y control de acceso | C6: RNF-05 | D6: Protección de endpoints y almacenamiento de contraseñas | E6: Invocar endpoints POST/PUT/DELETE sin credenciales; revisar cómo se guarda la contraseña en la tabla usuarios. | F6: Las peticiones sin autorización se rechazan (401/403) y las contraseñas están cifradas con hash, no en texto plano. | G6: Alta | H6: Ciclo 1 | I6: Por ejecutar | J6: 46329 | K6: Jorge Berroeta
A7: CP-06 | B7: B. Registro y gestión de pedidos | C7: RF-01 · HU-01 | D7: Registro de un pedido completo | E7: Datos: cliente, teléfono, categoría Torta, producto "Frambuesa Manjar Merengue", tamaño 20, cobertura, fecha y horario de entrega. Guardar. | F7: El pedido se guarda en la base de datos central en tiempo real, con código único, y aparece en la agenda de la fecha elegida. | G7: Alta | H7: Ciclo 1 | I7: Por ejecutar | J7: 46330 | K7: Camilo Rojas
A8: CP-07 | B8: B. Registro y gestión de pedidos | C8: RF-01 | D8: Validación de campos obligatorios | E8: Intentar guardar sin nombre del cliente, sin teléfono o sin fecha de entrega. | F8: No se guarda y se indican los campos faltantes. | G8: Alta | H8: Ciclo 1 | I8: Por ejecutar | J8: 46330 | K8: Camilo Rojas
A9: CP-08 | B9: B. Registro y gestión de pedidos | C9: RF-01 | D9: Cálculo del precio del pedido | E9: Crear pedidos con distintos tamaños y coberturas y comparar el precio con la tabla vigente. | F9: El precio final y el total coinciden con el precio base del tamaño más el adicional de la cobertura. | G9: Alta | H9: Ciclo 1 | I9: Por ejecutar | J9: 46330 | K9: Camilo Rojas
A10: CP-09 | B10: B. Registro y gestión de pedidos | C10: RF-01 | D10: Pedido en un día bloqueado | E10: Bloquear una fecha desde el calendario administrativo e intentar registrar un pedido para ese día. | F10: El sistema impide o advierte el agendamiento en la fecha cerrada. | G10: Alta | H10: Ciclo 1 | I10: Por ejecutar | J10: 46331 | K10: Camilo Rojas
A11: CP-10 | B11: B. Registro y gestión de pedidos | C11: RF-01 · RF-06 | D11: Edición de un pedido existente | E11: Abrir "Editar Pedido", modificar producto, tamaño y horario, y guardar. | F11: Los cambios persisten, se recalcula el precio y la agenda se actualiza. | G11: Media | H11: Ciclo 2 (regresión) | I11: Por ejecutar | J11: 46344 | K11: Camilo Rojas
A12: CP-11 | B12: B. Registro y gestión de pedidos | C12: RF-01 · RF-06 | D12: Eliminación de un pedido | E12: Desde la agenda, eliminar un pedido y confirmar. | F12: Se pide confirmación; el pedido desaparece de la agenda y del panel de producción. | G12: Media | H12: Ciclo 1 | I12: Por ejecutar | J12: 46331 | K12: Camilo Rojas
A13: CP-12 | B13: B. Registro y gestión de pedidos | C13: RF-01 · RF-06 | D13: Visualización de la agenda | E13: Navegar entre meses y seleccionar un día con y sin pedidos. | F13: Los días con pedidos muestran un marcador y se listan cliente, producto, hora y cantidad del día elegido. | G13: Media | H13: Ciclo 1 | I13: Por ejecutar | J13: 46331 | K13: Camilo Rojas
... A56: CP-55 | B56: J. Pruebas no funcionales | C56: RNF-07 | D56: Pruebas unitarias de la lógica de negocio | E56: Ejecutar la suite unitaria en cada sprint sobre pedidos, abonos y precios. | F56: Suite en verde y cobertura mínima propuesta de 60% en la lógica de negocio crítica. | G56: Media | H56: Ciclo 2 (regresión) | I56: Por ejecutar | J56: 46353 | K56: Renato Carreño

Sheet Defectos
A1: ID defecto | B1: Caso asociado | C1: Título | D1: Descripción y pasos para reproducir | E1: Resultado esperado vs. obtenido | F1: Severidad | G1: Estado | H1: Responsable | I1: Fecha de detección | J1: Fecha de cierre | K1: Evidencia / enlace a la incidencia
A2: DEF-001
A3: DEF-002
A4: DEF-003
A5: DEF-004
A6: DEF-005
A7: DEF-006
A8: DEF-007
A9: DEF-008
A10: DEF-009
A11: DEF-010
A12: DEF-011
A13: DEF-012
... A31: DEF-030

Sheet Ciclos
A1: Ciclo | B1: Semanas previstas | C1: Fecha de inicio | D1: Fecha de término | E1: Responsables | F1: Ejecutados | G1: Aprobados | H1: Fallidos | I1: Bloqueados | J1: % aprobación | K1: Observaciones
A2: Ciclo 1 | B2: S14 – S15 | F2: =G2+H2 -> 0 | G2: =COUNTIFS(Casos!$H$2:$H$56,$A2,Casos!$I$2:$I$56,"Aprobado") -> 0 | H2: =COUNTIFS(Casos!$H$2:$H$56,$A2,Casos!$I$2:$I$56,"Fallido") -> 0 | I2: =COUNTIFS(Casos!$H$2:$H$56,$A2,Casos!$I$2:$I$56,"Bloqueado") -> 0 | J2: =IF(F2=0,"",G2/F2)
A3: Ciclo 2 (regresión) | B3: S16 | F3: =G3+H3 -> 0 | G3: =COUNTIFS(Casos!$H$2:$H$56,$A3,Casos!$I$2:$I$56,"Aprobado") -> 0 | H3: =COUNTIFS(Casos!$H$2:$H$56,$A3,Casos!$I$2:$I$56,"Fallido") -> 0 | I3: =COUNTIFS(Casos!$H$2:$H$56,$A3,Casos!$I$2:$I$56,"Bloqueado") -> 0 | J3: =IF(F3=0,"",G3/F3)
A4: Aceptación (UAT) | B4: S16 – S17 | F4: =G4+H4 -> 0 | G4: =COUNTIFS(Casos!$H$2:$H$56,$A4,Casos!$I$2:$I$56,"Aprobado") -> 0 | H4: =COUNTIFS(Casos!$H$2:$H$56,$A4,Casos!$I$2:$I$56,"Fallido") -> 0 | I4: =COUNTIFS(Casos!$H$2:$H$56,$A4,Casos!$I$2:$I$56,"Bloqueado") -> 0 | J4: =IF(F4=0,"",G4/F4)
A6: Los contadores se calculan solos a partir de la columna Ciclo de la hoja Casos. Se considera ejecutado un caso Aprobado o Fallido; un caso Bloqueado no se cuenta como ejecutado.
