Workbook

Sheet Instrucciones
A1: Registro Scrum — Dulce Día
A3: Propósito | B3: Mantener actualizados el Product Backlog, el Sprint Backlog y el registro de reuniones del proyecto, y calcular automáticamente el avance de cada sprint.
A4: Importante | B4: Los estados que aparecen al comienzo (Hecho, En curso, Pendiente, Por hacer) son SUGERIDOS a partir de la evidencia disponible. El equipo debe confirmarlos o corregirlos. Las horas reales, las fechas y las reuniones realizadas parten vacías o en “No”: se completan con lo que de verdad ocurra.
A5: Celdas que se completan | B5: Las de fondo amarillo y letra azul: Product Backlog (prioridad, puntos, sprint, estado), Sprint Backlog (responsable, horas estimadas, estado, horas reales, fecha de cierre) y Reuniones (de Realizada a Acta). Todo lo demás se calcula solo. Las fechas previstas de las reuniones se calcularon desde la semana 1 (10/08/2026) y deben ajustarse a la realidad.
A6: Al cerrar cada sprint | B6: 1) En Sprint Backlog, actualizar el estado y las horas reales de cada tarea. 2) En Product Backlog, marcar como Hecho solo los ítems que cumplen la Definición de Hecho. 3) En Reuniones, registrar las reuniones realizadas, con su fecha, asistentes y ruta del acta en Git. 4) Revisar la hoja Avance (velocidad, quemado y horas) y comentarlo en la retrospectiva.
A7: Ítems fuera del sprint | B7: Los ítems con sprint “—” no están comprometidos en esta entrega. Si se incorporan, escribir el número de sprint en la columna Sprint.
A8: Hojas | B8: Product Backlog · Sprint Backlog · Reuniones · Avance (indicadores y gráficos).

Sheet Product Backlog
A1: ID | B1: Tipo | C1: Ítem | D1: Origen | E1: Prioridad | F1: Puntos | G1: Sprint | H1: Estado | I1: Criterios de aceptación
A2: PB-01 | B2: Habilitante | C2: Configurar el backend (API REST), la base de datos MySQL y el despliegue inicial en Railway. | D2: RNF-02, RNF-07 | E2: Debe | F2: 5 | G2: 1 | H2: Hecho | I2: La API responde desde Railway y la app se conecta a la base de datos.
A3: PB-02 | B3: Historia de usuario | C3: Como personal de atención, quiero iniciar sesión con mi rol para acceder solo a las funciones que me corresponden. | D3: HU-08 · RF-10 | E3: Debe | F3: 5 | G3: 1 | H3: Hecho | I3: Credenciales válidas e inválidas se manejan; solo se ven las funciones del rol.
A4: PB-03 | B4: Historia de usuario | C4: Como usuario interno, quiero consultar el catálogo por categorías (tortas, tartas y pastelitos) para elegir productos. | D4: HU-01 · RF-01 | E4: Debe | F4: 3 | G4: 1 | H4: Hecho | I4: El catálogo muestra nombre, tamaños y precio desde, por categoría.
A5: PB-04 | B5: Mejora técnica | C5: Agregar al modelo de datos las tablas de historial de estados y de abonos. | D5: RF-06 (brecha del modelo) | E5: Debería | F5: 5 | G5: 2 | H5: Pendiente | I5: Cada cambio de estado y cada abono queda registrado con fecha, hora y usuario.
A6: PB-05 | B6: Historia de usuario | C6: Como personal de atención, quiero registrar un pedido con el catálogo unificado para centralizar la información. | D6: HU-01 · RF-01 | E6: Debe | F6: 8 | G6: 2 | H6: Hecho | I6: El pedido se guarda con código único, estado Pendiente y fecha válida; aparece en la agenda.
A7: PB-06 | B7: Historia de usuario | C7: Como personal de atención, quiero ver, editar y eliminar pedidos en una agenda para mantener la información al día. | D7: HU-01 · RF-01, RF-06 | E7: Debe | F7: 5 | G7: 2 | H7: Hecho | I7: El calendario marca los días con pedidos; la edición recalcula el precio; eliminar pide confirmación.
A8: PB-07 | B8: Historia de usuario | C8: Como personal de producción, quiero ver los pedidos pendientes y su detalle para planificar la elaboración. | D8: HU-02 · RF-05 | E8: Debe | F8: 5 | G8: 2 | H8: Pendiente | I8: Producción ve los pedidos pendientes ordenados por fecha con su detalle completo.
A9: PB-08 | B9: Historia de usuario | C9: Como personal de producción, quiero recibir una notificación push de cada pedido nuevo para enterarme sin depender de WhatsApp. | D9: HU-02 · RF-05 | E9: Debe | F9: 5 | G9: 3 | H9: Hecho | I9: La notificación llega en menos de un minuto con producto y fecha.
A10: PB-09 | B10: Historia de usuario | C10: Como usuario del sistema, quiero asignar y actualizar el estado del pedido (Pendiente, Pagado, Entregado) para conocer su situación. | D10: HU-03 · RF-02 | E10: Debe | F10: 5 | G10: 3 | H10: En curso | I10: Solo se permiten los tres estados; cada cambio queda registrado con fecha y hora.
A11: PB-10 | B11: Historia de usuario | C11: Como personal de atención, quiero registrar abonos y ver el saldo pendiente para controlar los pagos. | D11: HU-04 · RF-03 | E11: Debe | F11: 8 | G11: 3 | H11: En curso | I11: El saldo se recalcula; se rechazan montos inválidos o mayores al saldo.
A12: PB-11 | B12: Mejora técnica | C12: Proteger el panel de administración con autenticación y control de acceso por rol. | D12: Hallazgo 1 · RNF-05 | E12: Debe | F12: 5 | G12: 3 | H12: Pendiente | I12: Sin sesión no se accede al panel ni a los endpoints de modificación.
A13: PB-12 | B13: Historia de usuario | C13: Como administrador, quiero editar precios masivamente y bloquear días y cupos para mantener actualizado el negocio. | D13: HU-07 · RF-11 · RF-01 | E13: Debe | F13: 5 | G13: 4 | H13: Hecho | I13: Los cambios de precios persisten; las fechas bloqueadas no admiten pedidos.
... A30: PB-29 | B30: Documentación | C30: Completar la documentación técnica final, el informe y la presentación del proyecto. | D30: Plan de trabajo | E30: Debe | F30: 8 | G30: 7 | H30: Pendiente | I30: Informe final con formato de la asignatura y presentación lista.
A31: PB-30 | B31: Historia de usuario | C31: Como cliente, quiero consultar el estado de mi pedido en línea. | D31: RF-08 · RF-02 | E31: Podría | F31: 3 | G31: — | H31: Pendiente | I31: El cliente ve el estado y la fecha de entrega con su número de pedido.
A32: PB-31 | B32: Historia de usuario | C32: Como administrador del sistema, quiero dar de alta nuevas pastelerías sin cambiar el código. | D32: HU-11 · RNF-03, RNF-08 | E32: Podría | F32: 8 | G32: — | H32: Pendiente | I32: Un nuevo cliente opera con sus datos separados de los de Dulce Día.

Sheet Sprint Backlog
A1: ID tarea | B1: Sprint | C1: Ítem | D1: Tarea | E1: Responsable | F1: Horas estimadas | G1: Estado | H1: Horas reales | I1: Fecha de cierre
A2: T-01 | B2: 1 | C2: PB-01 | D2: Configurar el proyecto Spring Boot y la conexión a MySQL | E2: Jorge Berroeta | F2: 6 | G2: Hecho
A3: T-02 | B3: 1 | C3: PB-01 | D3: Desplegar la API y la base de datos en Railway | E3: Jorge Berroeta | F3: 4 | G3: Hecho
A4: T-03 | B4: 1 | C4: PB-02 | D4: Implementar la autenticación y los roles en el backend | E4: Jorge Berroeta | F4: 6 | G4: Hecho
A5: T-04 | B5: 1 | C5: PB-02 | D5: Construir la pantalla de inicio de sesión de la app | E5: Jorge Berroeta | F5: 4 | G5: Hecho
A6: T-05 | B6: 1 | C6: PB-02 | D6: Documentar los usuarios y roles de prueba | E6: Renato Carreño | F6: 2 | G6: Hecho
A7: T-06 | B7: 1 | C7: PB-03 | D7: Exponer el endpoint del catálogo por categoría | E7: Jorge Berroeta | F7: 3 | G7: Hecho
A8: T-07 | B8: 1 | C8: PB-03 | D8: Construir la vista de catálogo con pestañas | E8: Camilo Rojas | F8: 4 | G8: Hecho
A9: T-08 | B9: 2 | C9: PB-04 | D9: Diseñar y agregar las tablas de historial de estados y abonos | E9: Jorge Berroeta | F9: 5 | G9: Por hacer
A10: T-09 | B10: 2 | C10: PB-04 | D10: Actualizar el diagrama entidad-relación y el de clases | E10: Renato Carreño | F10: 3 | G10: Por hacer
A11: T-10 | B11: 2 | C11: PB-05 | D11: Implementar el endpoint de creación de pedidos con validaciones | E11: Jorge Berroeta | F11: 8 | G11: Hecho
A12: T-11 | B12: 2 | C12: PB-05 | D12: Construir el formulario de pedido en la app | E12: Camilo Rojas | F12: 6 | G12: Hecho
A13: T-12 | B13: 2 | C13: PB-06 | D13: Implementar la agenda con calendario y lista de pedidos del día | E13: Camilo Rojas | F13: 6 | G13: Hecho
... A60: T-59 | B60: 7 | C60: PB-29 | D60: Revisar y corregir el informe final | E60: Jorge Berroeta | F60: 3 | G60: Por hacer

Sheet Reuniones
A1: N.º | B1: Sprint | C1: Tipo de reunión | D1: Semana prevista | E1: Fecha prevista | F1: Realizada | G1: Fecha realizada | H1: Duración (min) | I1: Asistentes | J1: Acuerdos principales | K1: Acta (ruta en Git)
A2: 1 | B2: 1 | C2: Planificación | D2: S5 | E2: 46272 | F2: No
A3: 2 | B3: 1 | C3: Seguimiento 1 | D3: S5 | E3: 46274 | F3: No
A4: 3 | B4: 1 | C4: Seguimiento 2 | D4: S6 | E4: 46281 | F4: No
A5: 4 | B5: 1 | C5: Revisión | D5: S6 | E5: 46283 | F5: No
A6: 5 | B6: 1 | C6: Retrospectiva | D6: S6 | E6: 46283 | F6: No
A7: 6 | B7: 2 | C7: Planificación | D7: S7 | E7: 46286 | F7: No
A8: 7 | B8: 2 | C8: Seguimiento 1 | D8: S7 | E8: 46288 | F8: No
A9: 8 | B9: 2 | C9: Seguimiento 2 | D9: S8 | E9: 46295 | F9: No
A10: 9 | B10: 2 | C10: Revisión | D10: S8 | E10: 46297 | F10: No
A11: 10 | B11: 2 | C11: Retrospectiva | D11: S8 | E11: 46297 | F11: No
A12: 11 | B12: 3 | C12: Planificación | D12: S9 | E12: 46300 | F12: No
A13: 12 | B13: 3 | C13: Seguimiento 1 | D13: S9 | E13: 46302 | F13: No
... A36: 35 | B36: 7 | C36: Retrospectiva | D36: S18 | E36: 46367 | F36: No

Sheet Avance
A1: Avance Scrum — Dulce Día
A2: Todo se calcula automáticamente desde las hojas Product Backlog, Sprint Backlog y Reuniones. No hay que escribir nada en esta hoja.
A4: Sprint | B4: Semanas | C4: Puntos comprometidos | D4: Puntos hechos | E4: % cumplimiento | F4: Puntos pendientes (burndown) | G4: Horas estimadas | H4: Horas reales | I4: Tareas totales | J4: Tareas hechas
A5: 1 | B5: S5 – S6 (07/09 – 20/09) | C5: =SUMIFS('Product Backlog'!$F$2:$F$32,'Product Backlog'!$G$2:$G$32,$A5) -> 13 | D5: =SUMIFS('Product Backlog'!$F$2:$F$32,'Product Backlog'!$G$2:$G$32,$A5,'Product Backlog'!$H$2:$H$32,"Hecho") -> 13 | E5: =IF(C5=0,0,D5/C5) -> 1 | F5: =SUM($C$5:$C$11)-SUM($D$5:D5) -> 149 | G5: =SUMIFS('Sprint Backlog'!$F$2:$F$60,'Sprint Backlog'!$B$2:$B$60,$A5) -> 29 | H5: =SUMIFS('Sprint Backlog'!$H$2:$H$60,'Sprint Backlog'!$B$2:$B$60,$A5) -> 0 | I5: =COUNTIFS('Sprint Backlog'!$B$2:$B$60,$A5) -> 7 | J5: =COUNTIFS('Sprint Backlog'!$B$2:$B$60,$A5,'Sprint Backlog'!$G$2:$G$60,"Hecho") -> 7
A6: 2 | B6: S7 – S8 (21/09 – 04/10) | C6: =SUMIFS('Product Backlog'!$F$2:$F$32,'Product Backlog'!$G$2:$G$32,$A6) -> 23 | D6: =SUMIFS('Product Backlog'!$F$2:$F$32,'Product Backlog'!$G$2:$G$32,$A6,'Product Backlog'!$H$2:$H$32,"Hecho") -> 13 | E6: =IF(C6=0,0,D6/C6) -> 0.56521739 | F6: =SUM($C$5:$C$11)-SUM($D$5:D6) -> 136 | G6: =SUMIFS('Sprint Backlog'!$F$2:$F$60,'Sprint Backlog'!$B$2:$B$60,$A6) -> 41 | H6: =SUMIFS('Sprint Backlog'!$H$2:$H$60,'Sprint Backlog'!$B$2:$B$60,$A6) -> 0 | I6: =COUNTIFS('Sprint Backlog'!$B$2:$B$60,$A6) -> 8 | J6: =COUNTIFS('Sprint Backlog'!$B$2:$B$60,$A6,'Sprint Backlog'!$G$2:$G$60,"Hecho") -> 4
A7: 3 | B7: S9 – S10 (05/10 – 18/10) | C7: =SUMIFS('Product Backlog'!$F$2:$F$32,'Product Backlog'!$G$2:$G$32,$A7) -> 23 | D7: =SUMIFS('Product Backlog'!$F$2:$F$32,'Product Backlog'!$G$2:$G$32,$A7,'Product Backlog'!$H$2:$H$32,"Hecho") -> 5 | E7: =IF(C7=0,0,D7/C7) -> 0.2173913 | F7: =SUM($C$5:$C$11)-SUM($D$5:D7) -> 131 | G7: =SUMIFS('Sprint Backlog'!$F$2:$F$60,'Sprint Backlog'!$B$2:$B$60,$A7) -> 43 | H7: =SUMIFS('Sprint Backlog'!$H$2:$H$60,'Sprint Backlog'!$B$2:$B$60,$A7) -> 0 | I7: =COUNTIFS('Sprint Backlog'!$B$2:$B$60,$A7) -> 9 | J7: =COUNTIFS('Sprint Backlog'!$B$2:$B$60,$A7,'Sprint Backlog'!$G$2:$G$60,"Hecho") -> 3
A8: 4 | B8: S11 – S12 (19/10 – 01/11) | C8: =SUMIFS('Product Backlog'!$F$2:$F$32,'Product Backlog'!$G$2:$G$32,$A8) -> 26 | D8: =SUMIFS('Product Backlog'!$F$2:$F$32,'Product Backlog'!$G$2:$G$32,$A8,'Product Backlog'!$H$2:$H$32,"Hecho") -> 18 | E8: =IF(C8=0,0,D8/C8) -> 0.69230769 | F8: =SUM($C$5:$C$11)-SUM($D$5:D8) -> 113 | G8: =SUMIFS('Sprint Backlog'!$F$2:$F$60,'Sprint Backlog'!$B$2:$B$60,$A8) -> 41 | H8: =SUMIFS('Sprint Backlog'!$H$2:$H$60,'Sprint Backlog'!$B$2:$B$60,$A8) -> 0 | I8: =COUNTIFS('Sprint Backlog'!$B$2:$B$60,$A8) -> 8 | J8: =COUNTIFS('Sprint Backlog'!$B$2:$B$60,$A8,'Sprint Backlog'!$G$2:$G$60,"Hecho") -> 5
A9: 5 | B9: S13 – S14 (02/11 – 15/11) | C9: =SUMIFS('Product Backlog'!$F$2:$F$32,'Product Backlog'!$G$2:$G$32,$A9) -> 27 | D9: =SUMIFS('Product Backlog'!$F$2:$F$32,'Product Backlog'!$G$2:$G$32,$A9,'Product Backlog'!$H$2:$H$32,"Hecho") -> 0 | E9: =IF(C9=0,0,D9/C9) -> 0 | F9: =SUM($C$5:$C$11)-SUM($D$5:D9) -> 113 | G9: =SUMIFS('Sprint Backlog'!$F$2:$F$60,'Sprint Backlog'!$B$2:$B$60,$A9) -> 46 | H9: =SUMIFS('Sprint Backlog'!$H$2:$H$60,'Sprint Backlog'!$B$2:$B$60,$A9) -> 0 | I9: =COUNTIFS('Sprint Backlog'!$B$2:$B$60,$A9) -> 10 | J9: =COUNTIFS('Sprint Backlog'!$B$2:$B$60,$A9,'Sprint Backlog'!$G$2:$G$60,"Hecho") -> 0
A10: 6 | B10: S15 – S16 (16/11 – 29/11) | C10: =SUMIFS('Product Backlog'!$F$2:$F$32,'Product Backlog'!$G$2:$G$32,$A10) -> 23 | D10: =SUMIFS('Product Backlog'!$F$2:$F$32,'Product Backlog'!$G$2:$G$32,$A10,'Product Backlog'!$H$2:$H$32,"Hecho") -> 0 | E10: =IF(C10=0,0,D10/C10) -> 0 | F10: =SUM($C$5:$C$11)-SUM($D$5:D10) -> 113 | G10: =SUMIFS('Sprint Backlog'!$F$2:$F$60,'Sprint Backlog'!$B$2:$B$60,$A10) -> 49 | H10: =SUMIFS('Sprint Backlog'!$H$2:$H$60,'Sprint Backlog'!$B$2:$B$60,$A10) -> 0 | I10: =COUNTIFS('Sprint Backlog'!$B$2:$B$60,$A10) -> 8 | J10: =COUNTIFS('Sprint Backlog'!$B$2:$B$60,$A10,'Sprint Backlog'!$G$2:$G$60,"Hecho") -> 0
A11: 7 | B11: S17 – S18 (30/11 – 13/12) | C11: =SUMIFS('Product Backlog'!$F$2:$F$32,'Product Backlog'!$G$2:$G$32,$A11) -> 27 | D11: =SUMIFS('Product Backlog'!$F$2:$F$32,'Product Backlog'!$G$2:$G$32,$A11,'Product Backlog'!$H$2:$H$32,"Hecho") -> 0 | E11: =IF(C11=0,0,D11/C11) -> 0 | F11: =SUM($C$5:$C$11)-SUM($D$5:D11) -> 113 | G11: =SUMIFS('Sprint Backlog'!$F$2:$F$60,'Sprint Backlog'!$B$2:$B$60,$A11) -> 48 | H11: =SUMIFS('Sprint Backlog'!$H$2:$H$60,'Sprint Backlog'!$B$2:$B$60,$A11) -> 0 | I11: =COUNTIFS('Sprint Backlog'!$B$2:$B$60,$A11) -> 9 | J11: =COUNTIFS('Sprint Backlog'!$B$2:$B$60,$A11,'Sprint Backlog'!$G$2:$G$60,"Hecho") -> 0
A12: Total | C12: =SUM(C5:C11) -> 162 | D12: =SUM(D5:D11) -> 49 | E12: =IF(C12=0,0,D12/C12) -> 0.30246914 | F12: =F11 -> 113 | G12: =SUM(G5:G11) -> 297 | H12: =SUM(H5:H11) -> 0 | I12: =SUM(I5:I11) -> 59 | J12: =SUM(J5:J11) -> 19
A14: Indicadores generales
A15: Ítems del Product Backlog | B15: =COUNTA('Product Backlog'!$A$2:$A$32) -> 31
A16: Ítems hechos | B16: =COUNTIF('Product Backlog'!$H$2:$H$32,"Hecho") -> 8
A17: Avance de puntos comprometidos | B17: =E12 -> 0.30246914
A18: Reuniones Scrum previstas | B18: =COUNTA(Reuniones!$A$2:$A$36) -> 35
A19: Reuniones realizadas | B19: =COUNTIF(Reuniones!$F$2:$F$36,"Sí") -> 0
A20: % de reuniones realizadas | B20: =IF(B18=0,0,B19/B18) -> 0
A23: Aporte por integrante (evidencia de equidad)
A24: Integrante | B24: Horas estimadas | C24: Horas reales | D24: Tareas asignadas | E24: Tareas hechas
A25: Jorge Berroeta | B25: =SUMIFS('Sprint Backlog'!$F$2:$F$60,'Sprint Backlog'!$E$2:$E$60,$A25) -> 141 | C25: =SUMIFS('Sprint Backlog'!$H$2:$H$60,'Sprint Backlog'!$E$2:$E$60,$A25) -> 0 | D25: =COUNTIFS('Sprint Backlog'!$E$2:$E$60,$A25) -> 26 | E25: =COUNTIFS('Sprint Backlog'!$E$2:$E$60,$A25,'Sprint Backlog'!$G$2:$G$60,"Hecho") -> 12
A26: Renato Carreño | B26: =SUMIFS('Sprint Backlog'!$F$2:$F$60,'Sprint Backlog'!$E$2:$E$60,$A26) -> 70 | C26: =SUMIFS('Sprint Backlog'!$H$2:$H$60,'Sprint Backlog'!$E$2:$E$60,$A26) -> 0 | D26: =COUNTIFS('Sprint Backlog'!$E$2:$E$60,$A26) -> 15 | E26: =COUNTIFS('Sprint Backlog'!$E$2:$E$60,$A26,'Sprint Backlog'!$G$2:$G$60,"Hecho") -> 3
A27: Camilo Rojas | B27: =SUMIFS('Sprint Backlog'!$F$2:$F$60,'Sprint Backlog'!$E$2:$E$60,$A27) -> 86 | C27: =SUMIFS('Sprint Backlog'!$H$2:$H$60,'Sprint Backlog'!$E$2:$E$60,$A27) -> 0 | D27: =COUNTIFS('Sprint Backlog'!$E$2:$E$60,$A27) -> 18 | E27: =COUNTIFS('Sprint Backlog'!$E$2:$E$60,$A27,'Sprint Backlog'!$G$2:$G$60,"Hecho") -> 4
